[{
	"id": "INTJ",
	"name": "建筑师/策划者人格",
	"slogan": "一切都在我的计划中",
	"percentage": 3,
  "animal": "123",
  "color": "pur",
  "tags": ["a", "b", "c", "d"],
  "description": "description",
  "character": "character",
  "career": "career",
  "advantages": "advantages",
  "disadvantages": "disadvantages",
  "famous": "famous",
  "couple": "couple",
  "linkEmoji": "linkEmoji",
  "linkProfile": "linkProfile",
  "meme": "meme"
}, {
	"id": "ENTJ",
	"name": "指挥官/CEO人格",
	"slogan": "S",
	"percentage": 4,
  "animal": "123",
  "color": "pur",
  "tags": ["a", "b", "c", "d"],
  "description": "description",
  "character": "character",
  "career": "career",
  "advantages": "advantages",
  "disadvantages": "disadvantages",
  "famous": "famous",
  "couple": "couple",
  "linkEmoji": "linkEmoji",
  "linkProfile": "linkProfile",
  "meme": "meme"
}, {
	"id": "INTP",
	"name": "逻辑学家/学者人格",
	"slogan": "让我观察一下再说！",
	"percentage": 3,
  "animal": "123",
  "color": "pur",
  "tags": ["观察者", "计划", "思考", "完美主义者", "洞察力", "独立自主", "略显冷漠"],
  "description": "INTP是自由的创意者，是思绪飞扬、思想深奥的学者，他们很容易转移注意力，脑中一刻都不曾停歇却有着无穷的创造力。对抽象概念的喜好以及深入理解，使他们刻意从事具有创造性和挑战性的任何工作。他们是淡然随和的理性者，且多数慢性子。 如果现实准许，INTP多数最终会选择遁世，做个隐士、居士一类的，或者躲在某个犄角旮旯观察着世间规律，构筑自己的思想世界。",
  "character": "他们喜欢在工作中寻找乐趣，独立思考，喜欢自立性强的工作。他们把生活看作学习。因此，任何能够开发智力的活动都极具价值，从动手拆装到起草项目建议书，都是一个个学习和成长的机会。这是激励INTP的主要驱动力。INTP的思想深奥，非常容易被复杂和神秘事物吸引。对INTP来说复杂性似乎先天的无需证明的一种价值。他们会本能地忽略掉那些简单的、一眼就能看透的东西，转而去关注那些复杂的、需要仔细琢磨才能理解和参透的东西。",
  "career": ["偏好的职业领域：计算机应用与开发、理论研究、学术领域、专业领域、创造性领域等。","  偏好的典型职业：建筑师、计算机软件设计人员、网络专家、网站设计人员、系统分析人员、信息服务开发商、金融规划师、风险投资商、调查员、财务分析、经济学者、大学教授、知识产权律师、音乐家、神经科医师、分析心理学专家、企业金融律师等。" ],
  "advantages": ["能够理解非常复杂和高度抽象的概念", "杰出的创造性地解决问题的技能", "独立自主，探险精神、创造意识以及克服困难的勇气", "能够综合考虑和运用大量的信息", "需信息时理智的好奇心、独特的洞悉力", "即使在压力很大的情况下也能逻辑分析事物"],
  "disadvantages": ["办事情可能条理不清，容易发生紊乱", "可能会不恰当地运用自己的能力和社会经历", "对思维狭窄和思想固执的人缺乏耐心", "不喜欢按传统的、公式化的方式来办事", "问题一旦解决，兴趣便不复存在", "可能过于理论化，而忽视或无视现实性"],
  "famous": "famous",
  "couple": "couple",
  "linkEmoji": "linkEmoji",
  "linkProfile": "linkProfile",
  "meme": "meme"
}, {
	"id": "ENTP",
	"name": "辩论家/发起者人格",
	"slogan": "T",
	"percentage": 3,
  "animal": "123",
  "color": "pur",
  "tags": ["a", "b", "c", "d"],
  "description": "description",
  "character": "character",
  "career": "career",
  "advantages": "advantages",
  "disadvantages": "disadvantages",
  "famous": "famous",
  "couple": "couple",
  "linkEmoji": "linkEmoji",
  "linkProfile": "linkProfile",
  "meme": "meme"
}, {
	"id": "ISTJ",
	"name": "检查者/鉴定者人格",
	"slogan": "我不喜欢迟到的人",
	"percentage": 3,
  "animal": "123",
  "color": "pur",
  "tags": ["a", "b", "c", "d"],
  "description": "description",
  "character": "character",
  "career": "career",
  "advantages": "advantages",
  "disadvantages": "disadvantages",
  "famous": "famous",
  "couple": "couple",
  "linkEmoji": "linkEmoji",
  "linkProfile": "linkProfile",
  "meme": "meme"
}, {
	"id": "ISFJ",
	"name": "守护者/保护者人格",
	"slogan": "T",
	"percentage": 4,
  "animal": "123",
  "color": "pur",
  "tags": ["a", "b", "c", "d"],
  "description": "description",
  "character": "character",
  "career": "career",
  "advantages": "advantages",
  "disadvantages": "disadvantages",
  "famous": "famous",
  "couple": "couple",
  "linkEmoji": "linkEmoji",
  "linkProfile": "linkProfile",
  "meme": "meme"
}, {
	"id": "ESFJ",
	"name": "领主/东道主人格",
	"slogan": "E",
  "percentage": 3,
  "animal": "123",
  "color": "pur",
  "tags": ["a", "b", "c", "d"],
  "description": "description",
  "character": "character",
  "career": "career",
  "advantages": "advantages",
  "disadvantages": "disadvantages",
  "famous": "famous",
  "couple": "couple",
  "linkEmoji": "linkEmoji",
  "linkProfile": "linkProfile",
  "meme": "meme"
}, {
	"id": "ESTJ",
	"name": "总经理/大总管人格",
	"slogan": "J",
  "percentage": 4,
  "animal": "123",
  "color": "pur",
  "tags": ["a", "b", "c", "d"],
  "description": "description",
  "character": "character",
  "career": "career",
  "advantages": "advantages",
  "disadvantages": "disadvantages",
  "famous": "famous",
  "couple": "couple",
  "linkEmoji": "linkEmoji",
  "linkProfile": "linkProfile",
  "meme": "meme"
}, {
	"id": "INFJ",
	"name": "劝导者/提倡者人格",
	"slogan": "J",
  "percentage": 4,
  "animal": "123",
  "color": "pur",
  "tags": ["a", "b", "c", "d"],
  "description": "description",
  "character": "character",
  "career": "career",
  "advantages": "advantages",
  "disadvantages": "disadvantages",
  "famous": "famous",
  "couple": "couple",
  "linkEmoji": "linkEmoji",
  "linkProfile": "linkProfile",
  "meme": "meme"
}, {
	"id": "INFP",
	"name": "治愈者/梦想家人格",
	"slogan": "S",
  "percentage": 3,
  "animal": "123",
  "color": "pur",
  "tags": ["a", "b", "c", "d"],
  "description": "description",
  "character": "character",
  "career": "career",
  "advantages": "advantages",
  "disadvantages": "disadvantages",
  "famous": "famous",
  "couple": "couple",
  "linkEmoji": "linkEmoji",
  "linkProfile": "linkProfile",
  "meme": "meme"
}, {
	"id": "ENFJ",
	"name": "拥护者/教导者人格",
	"slogan": "J",
  "percentage": 4,
  "animal": "123",
  "color": "pur",
  "tags": ["a", "b", "c", "d"],
  "description": "description",
  "character": "character",
  "career": "career",
  "advantages": "advantages",
  "disadvantages": "disadvantages",
  "famous": "famous",
  "couple": "couple",
  "linkEmoji": "linkEmoji",
  "linkProfile": "linkProfile",
  "meme": "meme"
}, {
	"id": "ENFP",
	"name": "竞选者/宣传者人格",
	"slogan": "J",
  "percentage": 3,
  "animal": "123",
  "color": "pur",
  "tags": ["a", "b", "c", "d"],
  "description": "description",
  "character": "character",
  "career": "career",
  "advantages": "advantages",
  "disadvantages": "disadvantages",
  "famous": "famous",
  "couple": "couple",
  "linkEmoji": "linkEmoji",
  "linkProfile": "linkProfile",
  "meme": "meme"
}, {
	"id": "ISTP",
	"name": "手艺人/机械师人格",
	"slogan": "E",
  "percentage": 4,
  "animal": "123",
  "color": "pur",
  "tags": ["a", "b", "c", "d"],
  "description": "description",
  "character": "character",
  "career": "career",
  "advantages": "advantages",
  "disadvantages": "disadvantages",
  "famous": "famous",
  "couple": "couple",
  "linkEmoji": "linkEmoji",
  "linkProfile": "linkProfile",
  "meme": "meme"
}, {
	"id": "ISFP",
	"name": "艺术家/创作者人格",
	"slogan": "E",
  "percentage": 4,
  "animal": "123",
  "color": "pur",
  "tags": ["a", "b", "c", "d"],
  "description": "description",
  "character": "character",
  "career": "career",
  "advantages": "advantages",
  "disadvantages": "disadvantages",
  "famous": "famous",
  "couple": "couple",
  "linkEmoji": "linkEmoji",
  "linkProfile": "linkProfile",
  "meme": "meme"
}, {
	"id": "ESTP",
	"name": "冒险家/说服者人格",
	"slogan": "S",
  "percentage": 3,
  "animal": "123",
  "color": "pur",
  "tags": ["a", "b", "c", "d"],
  "description": "description",
  "character": "character",
  "career": "career",
  "advantages": "advantages",
  "disadvantages": "disadvantages",
  "famous": "famous",
  "couple": "couple",
  "linkEmoji": "linkEmoji",
  "linkProfile": "linkProfile",
  "meme": "meme"
}, {
	"id": "ESFP",
	"name": "表演者/演示者人格",
	"slogan": "S",
  "percentage": 4,
  "animal": "123",
  "color": "pur",
  "tags": ["a", "b", "c", "d"],
  "description": "description",
  "character": "character",
  "career": "career",
  "advantages": "advantages",
  "disadvantages": "disadvantages",
  "famous": "famous",
  "couple": "couple",
  "linkEmoji": "linkEmoji",
  "linkProfile": "linkProfile",
  "meme": "meme"
}]